setup.cfg
setup.py
plasma/__init__.py
plasma/conf.py
plasma/conf_parser.py
plasma/jet_signals.py
plasma.egg-info/PKG-INFO
plasma.egg-info/SOURCES.txt
plasma.egg-info/dependency_links.txt
plasma.egg-info/requires.txt
plasma.egg-info/top_level.txt
plasma/models/__init__.py
plasma/models/builder.py
plasma/models/loader.py
plasma/models/mpi_runner.py
plasma/models/runner.py
plasma/models/targets.py
plasma/preprocessor/__init__.py
plasma/preprocessor/normalize.py
plasma/preprocessor/preprocess.py
plasma/primitives/__init__.py
plasma/primitives/shots.py
plasma/utils/__init__.py
plasma/utils/evaluation.py
plasma/utils/mpi_launch_tensorflow.py
plasma/utils/performance.py
plasma/utils/processing.py
tests/__init__.py
tests/testbasic.py