Metadata-Version: 1.1
Name: plasma
Version: 0.0.2
Summary: PPPL deep learning package.
Home-page: UNKNOWN
Author: Alexey Svyatkovskiy
Author-email: alexeys@princeton.edu
License: UNKNOWN
Download-URL: https://github.com/PPPLDeepLearning/plasma-python
Platform: Any
Classifier: Development Status :: 3 - Alpha
Classifier: Environment :: Console
Classifier: Intended Audience :: Science/Research
Classifier: Programming Language :: Python
Classifier: Topic :: Scientific/Engineering :: Information Analysis
Classifier: Topic :: Scientific/Engineering :: Physics
Classifier: Topic :: Scientific/Engineering :: Mathematics
Classifier: Topic :: System :: Distributed Computing
